{"bitcoin-plus": {"1541030400": {"ts": 1541030400, "volume_24h": 2487.0, "market_cap": 522959.0, "price": 4.52, "percent_change_24h": 0, "percent_change_7d": 0}, "1541116800": {"ts": 1541116800, "volume_24h": 6352.0, "market_cap": 638142.0, "price": 5.51, "percent_change_24h": 21.9027, "percent_change_7d": 0}, "1541203200": {"ts": 1541203200, "volume_24h": 3242.0, "market_cap": 608014.0, "price": 5.25, "percent_change_24h": -4.7187, "percent_change_7d": 0}, "1541289600": {"ts": 1541289600, "volume_24h": 3332.0, "market_cap": 641154.0, "price": 5.53, "percent_change_24h": 5.3333, "percent_change_7d": 0}, "1541376000": {"ts": 1541376000, "volume_24h": 3640.0, "market_cap": 637273.0, "price": 5.5, "percent_change_24h": -0.5425, "percent_change_7d": 0}, "1541462400": {"ts": 1541462400, "volume_24h": 1462.0, "market_cap": 684681.0, "price": 5.92, "percent_change_24h": 7.6364, "percent_change_7d": 0}, "1541548800": {"ts": 1541548800, "volume_24h": 1465.0, "market_cap": 707483.0, "price": 6.1, "percent_change_24h": 3.0405, "percent_change_7d": 0}, "1541635200": {"ts": 1541635200, "volume_24h": 5328.0, "market_cap": 753899.0, "price": 6.49, "percent_change_24h": 6.3934, "percent_change_7d": 43.5841}, "1541721600": {"ts": 1541721600, "volume_24h": 1775.0, "market_cap": 718070.0, "price": 6.18, "percent_change_24h": -4.7766, "percent_change_7d": 12.1597}, "1541808000": {"ts": 1541808000, "volume_24h": 2085.0, "market_cap": 754287.0, "price": 6.49, "percent_change_24h": 5.0162, "percent_change_7d": 23.619}, "1541894400": {"ts": 1541894400, "volume_24h": 2528.0, "market_cap": 812184.0, "price": 6.99, "percent_change_24h": 7.7042, "percent_change_7d": 26.4014}, "1541980800": {"ts": 1541980800, "volume_24h": 1471.0, "market_cap": 786900.0, "price": 6.77, "percent_change_24h": -3.1474, "percent_change_7d": 23.0909}, "1542067200": {"ts": 1542067200, "volume_24h": 3752.0, "market_cap": 808472.0, "price": 6.95, "percent_change_24h": 2.6588, "percent_change_7d": 17.3986}, "1542153600": {"ts": 1542153600, "volume_24h": 4301.0, "market_cap": 749253.0, "price": 6.44, "percent_change_24h": -7.3381, "percent_change_7d": 5.5738}, "1542240000": {"ts": 1542240000, "volume_24h": 1129.0, "market_cap": 800634.0, "price": 6.88, "percent_change_24h": 6.8323, "percent_change_7d": 6.0092}, "1542326400": {"ts": 1542326400, "volume_24h": 3604.0, "market_cap": 784170.0, "price": 6.74, "percent_change_24h": -2.0349, "percent_change_7d": 9.0615}, "1542412800": {"ts": 1542412800, "volume_24h": 968.0, "market_cap": 729432.0, "price": 6.26, "percent_change_24h": -7.1217, "percent_change_7d": -3.5439}, "1542499200": {"ts": 1542499200, "volume_24h": 1537.0, "market_cap": 748030.0, "price": 6.42, "percent_change_24h": 2.5559, "percent_change_7d": -8.1545}, "1542585600": {"ts": 1542585600, "volume_24h": 6517.0, "market_cap": 895959.0, "price": 7.69, "percent_change_24h": 19.7819, "percent_change_7d": 13.5894}, "1542672000": {"ts": 1542672000, "volume_24h": 8408.0, "market_cap": 788245.0, "price": 6.76, "percent_change_24h": -12.0936, "percent_change_7d": -2.7338}, "1542758400": {"ts": 1542758400, "volume_24h": 4871.0, "market_cap": 852676.0, "price": 7.31, "percent_change_24h": 8.1361, "percent_change_7d": 13.5093}, "1542844800": {"ts": 1542844800, "volume_24h": 2527.0, "market_cap": 849468.0, "price": 7.28, "percent_change_24h": -0.4104, "percent_change_7d": 5.814}, "1542931200": {"ts": 1542931200, "volume_24h": 3957.0, "market_cap": 892741.0, "price": 7.65, "percent_change_24h": 5.0824, "percent_change_7d": 13.5015}, "1543017600": {"ts": 1543017600, "volume_24h": 5074.0, "market_cap": 766816.0, "price": 6.57, "percent_change_24h": -14.1176, "percent_change_7d": 4.9521}, "1543104000": {"ts": 1543104000, "volume_24h": 4260.0, "market_cap": 777618.0, "price": 6.66, "percent_change_24h": 1.3699, "percent_change_7d": 3.7383}, "1543190400": {"ts": 1543190400, "volume_24h": 2042.0, "market_cap": 764248.0, "price": 6.54, "percent_change_24h": -1.8018, "percent_change_7d": -14.9545}, "1543276800": {"ts": 1543276800, "volume_24h": 1826.0, "market_cap": 750703.0, "price": 6.42, "percent_change_24h": -1.8349, "percent_change_7d": -5.0296}, "1543363200": {"ts": 1543363200, "volume_24h": 4960.0, "market_cap": 925261.0, "price": 7.91, "percent_change_24h": 23.2087, "percent_change_7d": 8.2079}, "1543449600": {"ts": 1543449600, "volume_24h": 3888.0, "market_cap": 897286.0, "price": 7.67, "percent_change_24h": -3.0341, "percent_change_7d": 5.3571}, "1543536000": {"ts": 1543536000, "volume_24h": 508.0, "market_cap": 825301.0, "price": 7.05, "percent_change_24h": -8.0834, "percent_change_7d": -7.8431}, "1543622400": {"ts": 1543622400, "volume_24h": 4353.0, "market_cap": 812207.0, "price": 6.94, "percent_change_24h": -1.5603, "percent_change_7d": 5.6317}, "1543708800": {"ts": 1543708800, "volume_24h": 146.0, "market_cap": 811551.0, "price": 6.93, "percent_change_24h": -0.1441, "percent_change_7d": 4.0541}, "1543795200": {"ts": 1543795200, "volume_24h": 1129.0, "market_cap": 701436.0, "price": 5.99, "percent_change_24h": -13.5642, "percent_change_7d": -8.4098}, "1543881600": {"ts": 1543881600, "volume_24h": 181.0, "market_cap": 732351.0, "price": 6.25, "percent_change_24h": 4.3406, "percent_change_7d": -2.648}, "1543968000": {"ts": 1543968000, "volume_24h": 155.0, "market_cap": 716281.0, "price": 6.11, "percent_change_24h": -2.24, "percent_change_7d": -22.756}, "1544054400": {"ts": 1544054400, "volume_24h": 600.0, "market_cap": 631644.0, "price": 5.39, "percent_change_24h": -11.784, "percent_change_7d": -29.7262}, "1544140800": {"ts": 1544140800, "volume_24h": 1038.0, "market_cap": 701450.0, "price": 5.98, "percent_change_24h": 10.9462, "percent_change_7d": -15.1773}, "1544227200": {"ts": 1544227200, "volume_24h": 463.0, "market_cap": 753936.0, "price": 6.43, "percent_change_24h": 7.5251, "percent_change_7d": -7.3487}, "1544313600": {"ts": 1544313600, "volume_24h": 911.0, "market_cap": 782792.0, "price": 6.67, "percent_change_24h": 3.7325, "percent_change_7d": -3.7518}, "1544400000": {"ts": 1544400000, "volume_24h": 1766.0, "market_cap": 751207.0, "price": 6.4, "percent_change_24h": -4.048, "percent_change_7d": 6.8447}, "1544486400": {"ts": 1544486400, "volume_24h": 1015.0, "market_cap": 740935.0, "price": 6.31, "percent_change_24h": -1.4063, "percent_change_7d": 0.96}, "1544572800": {"ts": 1544572800, "volume_24h": 1819.0, "market_cap": 637391.0, "price": 5.43, "percent_change_24h": -13.9461, "percent_change_7d": -11.1293}, "1544659200": {"ts": 1544659200, "volume_24h": 101.0, "market_cap": 672317.0, "price": 5.72, "percent_change_24h": 5.3407, "percent_change_7d": 6.1224}, "1544745600": {"ts": 1544745600, "volume_24h": 503.0, "market_cap": 648866.0, "price": 5.52, "percent_change_24h": -3.4965, "percent_change_7d": -7.6923}, "1544832000": {"ts": 1544832000, "volume_24h": 228.0, "market_cap": 634608.0, "price": 5.4, "percent_change_24h": -2.1739, "percent_change_7d": -16.0187}, "1544918400": {"ts": 1544918400, "volume_24h": 761.0, "market_cap": 690897.0, "price": 5.87, "percent_change_24h": 8.7037, "percent_change_7d": -11.994}, "1545004800": {"ts": 1545004800, "volume_24h": 1272.0, "market_cap": 1360710.0, "price": 11.56, "percent_change_24h": 96.9336, "percent_change_7d": 80.625}, "1545091200": {"ts": 1545091200, "volume_24h": 1519.0, "market_cap": 789283.0, "price": 6.71, "percent_change_24h": -41.955, "percent_change_7d": 6.3391}, "1545177600": {"ts": 1545177600, "volume_24h": 1140.0, "market_cap": 727660.0, "price": 6.18, "percent_change_24h": -7.8987, "percent_change_7d": 13.8122}, "1545264000": {"ts": 1545264000, "volume_24h": 1393.0, "market_cap": 813146.0, "price": 6.9, "percent_change_24h": 11.6505, "percent_change_7d": 20.6294}, "1545350400": {"ts": 1545350400, "volume_24h": 623.0, "market_cap": 740740.0, "price": 6.29, "percent_change_24h": -8.8406, "percent_change_7d": 13.9493}, "1545436800": {"ts": 1545436800, "volume_24h": 696.0, "market_cap": 862335.0, "price": 7.32, "percent_change_24h": 16.3752, "percent_change_7d": 35.5556}, "1545523200": {"ts": 1545523200, "volume_24h": 887.0, "market_cap": 770929.0, "price": 6.54, "percent_change_24h": -10.6557, "percent_change_7d": 11.414}, "1545609600": {"ts": 1545609600, "volume_24h": 2549.0, "market_cap": 720243.0, "price": 6.11, "percent_change_24h": -6.5749, "percent_change_7d": -47.1453}, "1545696000": {"ts": 1545696000, "volume_24h": 9318.0, "market_cap": 693282.0, "price": 5.88, "percent_change_24h": -3.7643, "percent_change_7d": -12.3696}, "1545782400": {"ts": 1545782400, "volume_24h": 432.0, "market_cap": 698389.0, "price": 5.92, "percent_change_24h": 0.6803, "percent_change_7d": -4.2071}, "1545868800": {"ts": 1545868800, "volume_24h": 1385.0, "market_cap": 606036.0, "price": 5.13, "percent_change_24h": -13.3446, "percent_change_7d": -25.6522}, "1545955200": {"ts": 1545955200, "volume_24h": 2100.0, "market_cap": 625766.0, "price": 5.3, "percent_change_24h": 3.3138, "percent_change_7d": -15.7393}, "1546041600": {"ts": 1546041600, "volume_24h": 735.0, "market_cap": 523196.0, "price": 4.43, "percent_change_24h": -16.4151, "percent_change_7d": -39.4809}, "1546128000": {"ts": 1546128000, "volume_24h": 2497.0, "market_cap": 530295.0, "price": 4.49, "percent_change_24h": 1.3544, "percent_change_7d": -31.3456}, "1546214400": {"ts": 1546214400, "volume_24h": 6481.0, "market_cap": 527732.0, "price": 4.46, "percent_change_24h": -0.6682, "percent_change_7d": -27.0049}, "1546300800": {"ts": 1546300800, "volume_24h": 14519.0, "market_cap": 668035.0, "price": 5.65, "percent_change_24h": 26.6816, "percent_change_7d": -3.9116}, "1546387200": {"ts": 1546387200, "volume_24h": 9825.0, "market_cap": 665722.0, "price": 5.63, "percent_change_24h": -0.354, "percent_change_7d": -4.8986}, "1546473600": {"ts": 1546473600, "volume_24h": 1243.0, "market_cap": 601377.0, "price": 5.08, "percent_change_24h": -9.7691, "percent_change_7d": -0.9747}, "1546560000": {"ts": 1546560000, "volume_24h": 309.0, "market_cap": 610773.0, "price": 5.16, "percent_change_24h": 1.5748, "percent_change_7d": -2.6415}, "1546646400": {"ts": 1546646400, "volume_24h": 623.0, "market_cap": 590795.0, "price": 4.99, "percent_change_24h": -3.2946, "percent_change_7d": 12.6411}, "1546732800": {"ts": 1546732800, "volume_24h": 95.0, "market_cap": 666082.0, "price": 5.62, "percent_change_24h": 12.6253, "percent_change_7d": 25.167}, "1546819200": {"ts": 1546819200, "volume_24h": 210.0, "market_cap": 678738.0, "price": 5.73, "percent_change_24h": 1.9573, "percent_change_7d": 28.4753}, "1546905600": {"ts": 1546905600, "volume_24h": 321.0, "market_cap": 670018.0, "price": 5.65, "percent_change_24h": -1.3962, "percent_change_7d": 0.0}, "1546992000": {"ts": 1546992000, "volume_24h": 314.0, "market_cap": 682999.0, "price": 5.76, "percent_change_24h": 1.9469, "percent_change_7d": 2.3091}, "1547078400": {"ts": 1547078400, "volume_24h": 3804.0, "market_cap": 554473.0, "price": 4.67, "percent_change_24h": -18.9236, "percent_change_7d": -8.0709}, "1547164800": {"ts": 1547164800, "volume_24h": 2084.0, "market_cap": 650042.0, "price": 5.48, "percent_change_24h": 17.3448, "percent_change_7d": 6.2016}, "1547251200": {"ts": 1547251200, "volume_24h": 4827.0, "market_cap": 654419.0, "price": 5.51, "percent_change_24h": 0.5474, "percent_change_7d": 10.4208}, "1547337600": {"ts": 1547337600, "volume_24h": 4462.0, "market_cap": 627502.0, "price": 5.29, "percent_change_24h": -3.9927, "percent_change_7d": -5.8719}, "1547424000": {"ts": 1547424000, "volume_24h": 4528.0, "market_cap": 665155.0, "price": 5.6, "percent_change_24h": 5.8601, "percent_change_7d": -2.2688}, "1547510400": {"ts": 1547510400, "volume_24h": 4177.0, "market_cap": 655141.0, "price": 5.52, "percent_change_24h": -1.4286, "percent_change_7d": -2.3009}, "1547596800": {"ts": 1547596800, "volume_24h": 3601.0, "market_cap": 612471.0, "price": 5.15, "percent_change_24h": -6.7029, "percent_change_7d": -10.5903}, "1547683200": {"ts": 1547683200, "volume_24h": 3495.0, "market_cap": 610318.0, "price": 5.13, "percent_change_24h": -0.3883, "percent_change_7d": 9.8501}, "1547769600": {"ts": 1547769600, "volume_24h": 3363.0, "market_cap": 621629.0, "price": 5.23, "percent_change_24h": 1.9493, "percent_change_7d": -4.562}, "1547856000": {"ts": 1547856000, "volume_24h": 3332.0, "market_cap": 544943.0, "price": 4.58, "percent_change_24h": -12.4283, "percent_change_7d": -16.8784}, "1547942400": {"ts": 1547942400, "volume_24h": 2742.0, "market_cap": 468197.0, "price": 3.93, "percent_change_24h": -14.1921, "percent_change_7d": -25.7089}, "1548028800": {"ts": 1548028800, "volume_24h": 2431.0, "market_cap": 425666.0, "price": 3.58, "percent_change_24h": -8.9059, "percent_change_7d": -36.0714}, "1548115200": {"ts": 1548115200, "volume_24h": 3109.0, "market_cap": 568854.0, "price": 4.78, "percent_change_24h": 33.5196, "percent_change_7d": -13.4058}, "1548201600": {"ts": 1548201600, "volume_24h": 3424.0, "market_cap": 584189.0, "price": 4.9, "percent_change_24h": 2.5105, "percent_change_7d": -4.8544}, "1548288000": {"ts": 1548288000, "volume_24h": 3506.0, "market_cap": 622923.0, "price": 5.23, "percent_change_24h": 6.7347, "percent_change_7d": 1.9493}, "1548374400": {"ts": 1548374400, "volume_24h": 3435.0, "market_cap": 625874.0, "price": 5.25, "percent_change_24h": 0.3824, "percent_change_7d": 0.3824}, "1548460800": {"ts": 1548460800, "volume_24h": 3290.0, "market_cap": 646830.0, "price": 5.42, "percent_change_24h": 3.2381, "percent_change_7d": 18.3406}, "1548547200": {"ts": 1548547200, "volume_24h": 2974.0, "market_cap": 595974.0, "price": 5.0, "percent_change_24h": -7.7491, "percent_change_7d": 27.2265}, "1548633600": {"ts": 1548633600, "volume_24h": 3471.0, "market_cap": 556408.0, "price": 4.66, "percent_change_24h": -6.8, "percent_change_7d": 30.1676}, "1548720000": {"ts": 1548720000, "volume_24h": 2430.0, "market_cap": 525094.0, "price": 4.4, "percent_change_24h": -5.5794, "percent_change_7d": -7.9498}, "1548806400": {"ts": 1548806400, "volume_24h": 2597.0, "market_cap": 571737.0, "price": 4.79, "percent_change_24h": 8.8636, "percent_change_7d": -2.2449}}}