[{"ts": 1547424000, "volume_24h": 5420.0, "market_cap": 0.0, "price": 0.3674, "percent_change_24h": 0, "percent_change_7d": 0, "rank_volume": 1037, "rank_mcap": 1924, "rank_ratio": 0.539}, {"ts": 1547510400, "volume_24h": 4798.0, "market_cap": 0.0, "price": 0.3407, "percent_change_24h": -7.2673, "percent_change_7d": 0, "rank_volume": 1028, "rank_mcap": 1926, "rank_ratio": 0.5337}, {"ts": 1547596800, "volume_24h": 6316.0, "market_cap": 161574.0, "price": 0.2542, "percent_change_24h": -25.3889, "percent_change_7d": 0, "rank_volume": 1011, "rank_mcap": 1264, "rank_ratio": 0.7998}, {"ts": 1547683200, "volume_24h": 15541.0, "market_cap": 272678.0, "price": 0.429, "percent_change_24h": 68.7648, "percent_change_7d": 0, "rank_volume": 837, "rank_mcap": 1139, "rank_ratio": 0.7349}, {"ts": 1547769600, "volume_24h": 9353.0, "market_cap": 218905.0, "price": 0.3444, "percent_change_24h": -19.7203, "percent_change_7d": 0, "rank_volume": 928, "rank_mcap": 1190, "rank_ratio": 0.7798}, {"ts": 1547856000, "volume_24h": 7578.0, "market_cap": 241363.0, "price": 0.3797, "percent_change_24h": 10.2497, "percent_change_7d": 0, "rank_volume": 962, "rank_mcap": 1171, "rank_ratio": 0.8215}, {"ts": 1547942400, "volume_24h": 7231.0, "market_cap": 225174.0, "price": 0.3543, "percent_change_24h": -6.6895, "percent_change_7d": 0, "rank_volume": 955, "rank_mcap": 1176, "rank_ratio": 0.8121}, {"ts": 1548028800, "volume_24h": 4701.0, "market_cap": 205923.0, "price": 0.324, "percent_change_24h": -8.5521, "percent_change_7d": -11.8127, "rank_volume": 1014, "rank_mcap": 1204, "rank_ratio": 0.8422}, {"ts": 1548115200, "volume_24h": 10904.0, "market_cap": 210536.0, "price": 0.3312, "percent_change_24h": 2.2222, "percent_change_7d": -2.7884, "rank_volume": 900, "rank_mcap": 1194, "rank_ratio": 0.7538}, {"ts": 1548201600, "volume_24h": 10846.0, "market_cap": 206502.0, "price": 0.3249, "percent_change_24h": -1.9022, "percent_change_7d": 27.8127, "rank_volume": 907, "rank_mcap": 1203, "rank_ratio": 0.7539}, {"ts": 1548288000, "volume_24h": 7941.0, "market_cap": 213059.0, "price": 0.3352, "percent_change_24h": 3.1702, "percent_change_7d": -21.8648, "rank_volume": 924, "rank_mcap": 1193, "rank_ratio": 0.7745}, {"ts": 1548374400, "volume_24h": 11826.0, "market_cap": 218231.0, "price": 0.3433, "percent_change_24h": 2.4165, "percent_change_7d": -0.3194, "rank_volume": 864, "rank_mcap": 1188, "rank_ratio": 0.7273}, {"ts": 1548460800, "volume_24h": 8983.0, "market_cap": 217853.0, "price": 0.3427, "percent_change_24h": -0.1748, "percent_change_7d": -9.7445, "rank_volume": 914, "rank_mcap": 1182, "rank_ratio": 0.7733}, {"ts": 1548547200, "volume_24h": 9694.0, "market_cap": 198478.0, "price": 0.3123, "percent_change_24h": -8.8707, "percent_change_7d": -11.8544, "rank_volume": 911, "rank_mcap": 1202, "rank_ratio": 0.7579}, {"ts": 1548633600, "volume_24h": 6304.0, "market_cap": 187240.0, "price": 0.2549, "percent_change_24h": -18.3798, "percent_change_7d": -21.3272, "rank_volume": 992, "rank_mcap": 1208, "rank_ratio": 0.8212}, {"ts": 1548720000, "volume_24h": 12717.0, "market_cap": 187952.0, "price": 0.2534, "percent_change_24h": -0.5885, "percent_change_7d": -23.4903, "rank_volume": 842, "rank_mcap": 1200, "rank_ratio": 0.7017}, {"ts": 1548806400, "volume_24h": 4453.0, "market_cap": 194675.0, "price": 0.2572, "percent_change_24h": 1.4996, "percent_change_7d": -20.8372, "rank_volume": 1034, "rank_mcap": 1205, "rank_ratio": 0.8581}]