[{"ts": 1541030400, "volume_24h": 47426.0, "market_cap": 2548455.0, "price": 0.0364, "percent_change_24h": 0, "percent_change_7d": 0, "rank_volume": 720, "rank_mcap": 692, "rank_ratio": 1.0405}, {"ts": 1541116800, "volume_24h": 35948.0, "market_cap": 2499560.0, "price": 0.0357, "percent_change_24h": -1.9231, "percent_change_7d": 0, "rank_volume": 784, "rank_mcap": 705, "rank_ratio": 1.1121}, {"ts": 1541203200, "volume_24h": 5655.0, "market_cap": 2486687.0, "price": 0.0355, "percent_change_24h": -0.5602, "percent_change_7d": 0, "rank_volume": 1048, "rank_mcap": 703, "rank_ratio": 1.4908}, {"ts": 1541289600, "volume_24h": 35579.0, "market_cap": 2464798.0, "price": 0.0352, "percent_change_24h": -0.8451, "percent_change_7d": 0, "rank_volume": 760, "rank_mcap": 710, "rank_ratio": 1.0704}, {"ts": 1541376000, "volume_24h": 18178.0, "market_cap": 2562826.0, "price": 0.0366, "percent_change_24h": 3.9773, "percent_change_7d": 0, "rank_volume": 901, "rank_mcap": 697, "rank_ratio": 1.2927}, {"ts": 1541462400, "volume_24h": 30271.0, "market_cap": 2481731.0, "price": 0.036, "percent_change_24h": -1.6393, "percent_change_7d": 0, "rank_volume": 826, "rank_mcap": 706, "rank_ratio": 1.17}, {"ts": 1541548800, "volume_24h": 27225.0, "market_cap": 2621514.0, "price": 0.0374, "percent_change_24h": 3.8889, "percent_change_7d": 0, "rank_volume": 834, "rank_mcap": 704, "rank_ratio": 1.1847}, {"ts": 1541635200, "volume_24h": 142423.0, "market_cap": 2658817.0, "price": 0.038, "percent_change_24h": 1.6043, "percent_change_7d": 4.3956, "rank_volume": 512, "rank_mcap": 694, "rank_ratio": 0.7378}, {"ts": 1541721600, "volume_24h": 24977.0, "market_cap": 2604903.0, "price": 0.0372, "percent_change_24h": -2.1053, "percent_change_7d": 4.2017, "rank_volume": 841, "rank_mcap": 692, "rank_ratio": 1.2153}, {"ts": 1541808000, "volume_24h": 11110.0, "market_cap": 2523647.0, "price": 0.0361, "percent_change_24h": -2.957, "percent_change_7d": 1.6901, "rank_volume": 952, "rank_mcap": 705, "rank_ratio": 1.3504}, {"ts": 1541894400, "volume_24h": 20689.0, "market_cap": 2563953.0, "price": 0.0366, "percent_change_24h": 1.385, "percent_change_7d": 3.9773, "rank_volume": 844, "rank_mcap": 696, "rank_ratio": 1.2126}, {"ts": 1541980800, "volume_24h": 37030.0, "market_cap": 2622214.0, "price": 0.0375, "percent_change_24h": 2.459, "percent_change_7d": 2.459, "rank_volume": 780, "rank_mcap": 695, "rank_ratio": 1.1223}, {"ts": 1542067200, "volume_24h": 52726.0, "market_cap": 2598176.0, "price": 0.0371, "percent_change_24h": -1.0667, "percent_change_7d": 3.0556, "rank_volume": 689, "rank_mcap": 702, "rank_ratio": 0.9815}, {"ts": 1542153600, "volume_24h": 44933.0, "market_cap": 2118655.0, "price": 0.0303, "percent_change_24h": -18.3288, "percent_change_7d": -18.984, "rank_volume": 721, "rank_mcap": 716, "rank_ratio": 1.007}, {"ts": 1542240000, "volume_24h": 34760.0, "market_cap": 1958138.0, "price": 0.028, "percent_change_24h": -7.5908, "percent_change_7d": -26.3158, "rank_volume": 772, "rank_mcap": 737, "rank_ratio": 1.0475}, {"ts": 1542326400, "volume_24h": 12643.0, "market_cap": 1955401.0, "price": 0.0279, "percent_change_24h": -0.3571, "percent_change_7d": -25.0, "rank_volume": 924, "rank_mcap": 733, "rank_ratio": 1.2606}, {"ts": 1542412800, "volume_24h": 5848.0, "market_cap": 1899877.0, "price": 0.0271, "percent_change_24h": -2.8674, "percent_change_7d": -24.9307, "rank_volume": 1020, "rank_mcap": 741, "rank_ratio": 1.3765}, {"ts": 1542499200, "volume_24h": 4621.0, "market_cap": 1965810.0, "price": 0.0281, "percent_change_24h": 3.69, "percent_change_7d": -23.224, "rank_volume": 1071, "rank_mcap": 730, "rank_ratio": 1.4671}, {"ts": 1542585600, "volume_24h": 34479.0, "market_cap": 1622082.0, "price": 0.0232, "percent_change_24h": -17.4377, "percent_change_7d": -38.1333, "rank_volume": 755, "rank_mcap": 733, "rank_ratio": 1.03}, {"ts": 1542672000, "volume_24h": 49675.0, "market_cap": 1242584.0, "price": 0.0178, "percent_change_24h": -23.2759, "percent_change_7d": -52.0216, "rank_volume": 687, "rank_mcap": 774, "rank_ratio": 0.8876}, {"ts": 1542758400, "volume_24h": 28368.0, "market_cap": 1305423.0, "price": 0.0186, "percent_change_24h": 4.4944, "percent_change_7d": -38.6139, "rank_volume": 756, "rank_mcap": 770, "rank_ratio": 0.9818}, {"ts": 1542844800, "volume_24h": 6369.0, "market_cap": 1241751.0, "price": 0.0177, "percent_change_24h": -4.8387, "percent_change_7d": -36.7857, "rank_volume": 988, "rank_mcap": 769, "rank_ratio": 1.2848}, {"ts": 1542931200, "volume_24h": 10430.0, "market_cap": 1210335.0, "price": 0.0173, "percent_change_24h": -2.2599, "percent_change_7d": -37.9928, "rank_volume": 906, "rank_mcap": 764, "rank_ratio": 1.1859}, {"ts": 1543017600, "volume_24h": 8961.0, "market_cap": 1079736.0, "price": 0.0154, "percent_change_24h": -10.9827, "percent_change_7d": -43.1734, "rank_volume": 907, "rank_mcap": 767, "rank_ratio": 1.1825}, {"ts": 1543104000, "volume_24h": 7032.0, "market_cap": 1060493.0, "price": 0.0152, "percent_change_24h": -1.2987, "percent_change_7d": -45.9075, "rank_volume": 976, "rank_mcap": 785, "rank_ratio": 1.2433}, {"ts": 1543190400, "volume_24h": 9912.0, "market_cap": 1063314.0, "price": 0.0152, "percent_change_24h": 0.0, "percent_change_7d": -34.4828, "rank_volume": 904, "rank_mcap": 762, "rank_ratio": 1.1864}, {"ts": 1543276800, "volume_24h": 9237.0, "market_cap": 1034635.0, "price": 0.0148, "percent_change_24h": -2.6316, "percent_change_7d": -16.8539, "rank_volume": 921, "rank_mcap": 780, "rank_ratio": 1.1808}, {"ts": 1543363200, "volume_24h": 19010.0, "market_cap": 1228920.0, "price": 0.0176, "percent_change_24h": 18.9189, "percent_change_7d": -5.3763, "rank_volume": 835, "rank_mcap": 762, "rank_ratio": 1.0958}, {"ts": 1543449600, "volume_24h": 3963.0, "market_cap": 1214496.0, "price": 0.0174, "percent_change_24h": -1.1364, "percent_change_7d": -1.6949, "rank_volume": 1074, "rank_mcap": 762, "rank_ratio": 1.4094}, {"ts": 1543536000, "volume_24h": 4121.0, "market_cap": 1132629.0, "price": 0.0162, "percent_change_24h": -6.8966, "percent_change_7d": -6.3584, "rank_volume": 1057, "rank_mcap": 766, "rank_ratio": 1.3799}, {"ts": 1543622400, "volume_24h": 5667.0, "market_cap": 1237096.0, "price": 0.0177, "percent_change_24h": 9.2593, "percent_change_7d": 14.9351, "rank_volume": 983, "rank_mcap": 758, "rank_ratio": 1.2968}, {"ts": 1543708800, "volume_24h": 59792.0, "market_cap": 1287159.0, "price": 0.0184, "percent_change_24h": 3.9548, "percent_change_7d": 21.0526, "rank_volume": 592, "rank_mcap": 741, "rank_ratio": 0.7989}, {"ts": 1543795200, "volume_24h": 4741.0, "market_cap": 1179635.0, "price": 0.0169, "percent_change_24h": -8.1522, "percent_change_7d": 11.1842, "rank_volume": 1029, "rank_mcap": 747, "rank_ratio": 1.3775}, {"ts": 1543881600, "volume_24h": 8882.0, "market_cap": 1311360.0, "price": 0.0187, "percent_change_24h": 10.6509, "percent_change_7d": 26.3514, "rank_volume": 953, "rank_mcap": 732, "rank_ratio": 1.3019}, {"ts": 1543968000, "volume_24h": 4361.0, "market_cap": 1199215.0, "price": 0.0171, "percent_change_24h": -8.5561, "percent_change_7d": -2.8409, "rank_volume": 1039, "rank_mcap": 743, "rank_ratio": 1.3984}, {"ts": 1544054400, "volume_24h": 10761.0, "market_cap": 1046768.0, "price": 0.015, "percent_change_24h": -12.2807, "percent_change_7d": -13.7931, "rank_volume": 888, "rank_mcap": 757, "rank_ratio": 1.1731}, {"ts": 1544140800, "volume_24h": 8417.0, "market_cap": 1067749.0, "price": 0.0153, "percent_change_24h": 2.0, "percent_change_7d": -5.5556, "rank_volume": 941, "rank_mcap": 746, "rank_ratio": 1.2614}, {"ts": 1544227200, "volume_24h": 12570.0, "market_cap": 1143653.0, "price": 0.0163, "percent_change_24h": 6.5359, "percent_change_7d": -7.9096, "rank_volume": 833, "rank_mcap": 729, "rank_ratio": 1.1427}, {"ts": 1544313600, "volume_24h": 864513.0, "market_cap": 1455812.0, "price": 0.0208, "percent_change_24h": 27.6074, "percent_change_7d": 13.0435, "rank_volume": 153, "rank_mcap": 662, "rank_ratio": 0.2311}, {"ts": 1544400000, "volume_24h": 89056.0, "market_cap": 1316749.0, "price": 0.0188, "percent_change_24h": -9.6154, "percent_change_7d": 11.2426, "rank_volume": 519, "rank_mcap": 682, "rank_ratio": 0.761}, {"ts": 1544486400, "volume_24h": 60580.0, "market_cap": 1204320.0, "price": 0.0172, "percent_change_24h": -8.5106, "percent_change_7d": -8.0214, "rank_volume": 588, "rank_mcap": 701, "rank_ratio": 0.8388}, {"ts": 1544572800, "volume_24h": 26402.0, "market_cap": 1191755.0, "price": 0.017, "percent_change_24h": -1.1628, "percent_change_7d": -0.5848, "rank_volume": 724, "rank_mcap": 714, "rank_ratio": 1.014}, {"ts": 1544659200, "volume_24h": 5971.0, "market_cap": 1188684.0, "price": 0.017, "percent_change_24h": 0.0, "percent_change_7d": 13.3333, "rank_volume": 976, "rank_mcap": 703, "rank_ratio": 1.3883}, {"ts": 1544745600, "volume_24h": 19146.0, "market_cap": 1128879.0, "price": 0.0161, "percent_change_24h": -5.2941, "percent_change_7d": 5.2288, "rank_volume": 781, "rank_mcap": 709, "rank_ratio": 1.1016}, {"ts": 1544832000, "volume_24h": 7814.0, "market_cap": 1080462.0, "price": 0.0154, "percent_change_24h": -4.3478, "percent_change_7d": -5.5215, "rank_volume": 896, "rank_mcap": 725, "rank_ratio": 1.2359}, {"ts": 1544918400, "volume_24h": 5017.0, "market_cap": 1095207.0, "price": 0.0156, "percent_change_24h": 1.2987, "percent_change_7d": -25.0, "rank_volume": 969, "rank_mcap": 722, "rank_ratio": 1.3421}, {"ts": 1545004800, "volume_24h": 3434.0, "market_cap": 1170417.0, "price": 0.0167, "percent_change_24h": 7.0513, "percent_change_7d": -11.1702, "rank_volume": 1065, "rank_mcap": 722, "rank_ratio": 1.4751}, {"ts": 1545091200, "volume_24h": 15125.0, "market_cap": 1174437.0, "price": 0.0168, "percent_change_24h": 0.5988, "percent_change_7d": -2.3256, "rank_volume": 849, "rank_mcap": 740, "rank_ratio": 1.1473}, {"ts": 1545177600, "volume_24h": 30357.0, "market_cap": 1161098.0, "price": 0.0166, "percent_change_24h": -1.1905, "percent_change_7d": -2.3529, "rank_volume": 735, "rank_mcap": 756, "rank_ratio": 0.9722}, {"ts": 1545264000, "volume_24h": 15534.0, "market_cap": 1277081.0, "price": 0.0182, "percent_change_24h": 9.6386, "percent_change_7d": 7.0588, "rank_volume": 897, "rank_mcap": 751, "rank_ratio": 1.1944}, {"ts": 1545350400, "volume_24h": 9182.0, "market_cap": 1226988.0, "price": 0.0175, "percent_change_24h": -3.8462, "percent_change_7d": 8.6957, "rank_volume": 939, "rank_mcap": 742, "rank_ratio": 1.2655}, {"ts": 1545436800, "volume_24h": 8565.0, "market_cap": 1273369.0, "price": 0.0182, "percent_change_24h": 4.0, "percent_change_7d": 18.1818, "rank_volume": 909, "rank_mcap": 744, "rank_ratio": 1.2218}, {"ts": 1545523200, "volume_24h": 6081.0, "market_cap": 1233821.0, "price": 0.0176, "percent_change_24h": -3.2967, "percent_change_7d": 12.8205, "rank_volume": 1005, "rank_mcap": 766, "rank_ratio": 1.312}, {"ts": 1545609600, "volume_24h": 39972.0, "market_cap": 1304089.0, "price": 0.0186, "percent_change_24h": 5.6818, "percent_change_7d": 11.3772, "rank_volume": 704, "rank_mcap": 752, "rank_ratio": 0.9362}, {"ts": 1545696000, "volume_24h": 8346.0, "market_cap": 1173872.0, "price": 0.0168, "percent_change_24h": -9.6774, "percent_change_7d": 0.0, "rank_volume": 923, "rank_mcap": 758, "rank_ratio": 1.2177}, {"ts": 1545782400, "volume_24h": 10842.0, "market_cap": 1149195.0, "price": 0.0164, "percent_change_24h": -2.381, "percent_change_7d": -1.2048, "rank_volume": 885, "rank_mcap": 772, "rank_ratio": 1.1464}, {"ts": 1545868800, "volume_24h": 8657.0, "market_cap": 1123044.0, "price": 0.016, "percent_change_24h": -2.439, "percent_change_7d": -12.0879, "rank_volume": 922, "rank_mcap": 755, "rank_ratio": 1.2212}, {"ts": 1545955200, "volume_24h": 3453.0, "market_cap": 1212853.0, "price": 0.0173, "percent_change_24h": 8.125, "percent_change_7d": -1.1429, "rank_volume": 1096, "rank_mcap": 757, "rank_ratio": 1.4478}, {"ts": 1546041600, "volume_24h": 23379.0, "market_cap": 1114271.0, "price": 0.0159, "percent_change_24h": -8.0925, "percent_change_7d": -12.6374, "rank_volume": 760, "rank_mcap": 776, "rank_ratio": 0.9794}, {"ts": 1546128000, "volume_24h": 10464.0, "market_cap": 1091292.0, "price": 0.0156, "percent_change_24h": -1.8868, "percent_change_7d": -11.3636, "rank_volume": 896, "rank_mcap": 777, "rank_ratio": 1.1532}, {"ts": 1546214400, "volume_24h": 36634.0, "market_cap": 1031302.0, "price": 0.0147, "percent_change_24h": -5.7692, "percent_change_7d": -20.9677, "rank_volume": 669, "rank_mcap": 781, "rank_ratio": 0.8566}, {"ts": 1546300800, "volume_24h": 25039.0, "market_cap": 1097866.0, "price": 0.0157, "percent_change_24h": 6.8027, "percent_change_7d": -6.5476, "rank_volume": 731, "rank_mcap": 772, "rank_ratio": 0.9469}, {"ts": 1546387200, "volume_24h": 11195.0, "market_cap": 1091464.0, "price": 0.0156, "percent_change_24h": -0.6369, "percent_change_7d": -4.878, "rank_volume": 911, "rank_mcap": 788, "rank_ratio": 1.1561}, {"ts": 1546473600, "volume_24h": 10681.0, "market_cap": 1089498.0, "price": 0.0156, "percent_change_24h": 0.0, "percent_change_7d": -2.5, "rank_volume": 916, "rank_mcap": 781, "rank_ratio": 1.1729}, {"ts": 1546560000, "volume_24h": 16587.0, "market_cap": 1125924.0, "price": 0.0161, "percent_change_24h": 3.2051, "percent_change_7d": -6.9364, "rank_volume": 856, "rank_mcap": 778, "rank_ratio": 1.1003}, {"ts": 1546646400, "volume_24h": 6668.0, "market_cap": 1103170.0, "price": 0.0158, "percent_change_24h": -1.8634, "percent_change_7d": -0.6289, "rank_volume": 980, "rank_mcap": 775, "rank_ratio": 1.2645}, {"ts": 1546732800, "volume_24h": 9104.0, "market_cap": 1151498.0, "price": 0.0164, "percent_change_24h": 3.7975, "percent_change_7d": 5.1282, "rank_volume": 924, "rank_mcap": 781, "rank_ratio": 1.1831}, {"ts": 1546819200, "volume_24h": 3680.0, "market_cap": 1100682.0, "price": 0.0157, "percent_change_24h": -4.2683, "percent_change_7d": 6.8027, "rank_volume": 1075, "rank_mcap": 780, "rank_ratio": 1.3782}, {"ts": 1546905600, "volume_24h": 3423.0, "market_cap": 1087803.0, "price": 0.0155, "percent_change_24h": -1.2739, "percent_change_7d": -1.2739, "rank_volume": 1092, "rank_mcap": 785, "rank_ratio": 1.3911}, {"ts": 1546992000, "volume_24h": 13232.0, "market_cap": 1099312.0, "price": 0.0157, "percent_change_24h": 1.2903, "percent_change_7d": 0.641, "rank_volume": 880, "rank_mcap": 788, "rank_ratio": 1.1168}, {"ts": 1547078400, "volume_24h": 10158.0, "market_cap": 1035255.0, "price": 0.0148, "percent_change_24h": -5.7325, "percent_change_7d": -5.1282, "rank_volume": 942, "rank_mcap": 779, "rank_ratio": 1.2092}, {"ts": 1547164800, "volume_24h": 2953.0, "market_cap": 1017470.0, "price": 0.0145, "percent_change_24h": -2.027, "percent_change_7d": -9.9379, "rank_volume": 1126, "rank_mcap": 785, "rank_ratio": 1.4344}, {"ts": 1547251200, "volume_24h": 3366.0, "market_cap": 984955.0, "price": 0.0141, "percent_change_24h": -2.7586, "percent_change_7d": -10.7595, "rank_volume": 1065, "rank_mcap": 790, "rank_ratio": 1.3481}, {"ts": 1547337600, "volume_24h": 6969.0, "market_cap": 1006187.0, "price": 0.0144, "percent_change_24h": 2.1277, "percent_change_7d": -12.1951, "rank_volume": 954, "rank_mcap": 770, "rank_ratio": 1.239}, {"ts": 1547424000, "volume_24h": 7297.0, "market_cap": 1048746.0, "price": 0.015, "percent_change_24h": 4.1667, "percent_change_7d": -4.4586, "rank_volume": 982, "rank_mcap": 777, "rank_ratio": 1.2638}, {"ts": 1547510400, "volume_24h": 7931.0, "market_cap": 1038456.0, "price": 0.0148, "percent_change_24h": -1.3333, "percent_change_7d": -4.5161, "rank_volume": 968, "rank_mcap": 772, "rank_ratio": 1.2539}, {"ts": 1547596800, "volume_24h": 3209.0, "market_cap": 1050307.0, "price": 0.015, "percent_change_24h": 1.3514, "percent_change_7d": -4.4586, "rank_volume": 1095, "rank_mcap": 774, "rank_ratio": 1.4147}, {"ts": 1547683200, "volume_24h": 684295.0, "market_cap": 1186443.0, "price": 0.0169, "percent_change_24h": 12.6667, "percent_change_7d": 14.1892, "rank_volume": 213, "rank_mcap": 741, "rank_ratio": 0.2874}, {"ts": 1547769600, "volume_24h": 183223.0, "market_cap": 1200438.0, "price": 0.0171, "percent_change_24h": 1.1834, "percent_change_7d": 17.931, "rank_volume": 401, "rank_mcap": 735, "rank_ratio": 0.5456}, {"ts": 1547856000, "volume_24h": 43520.0, "market_cap": 1150391.0, "price": 0.0164, "percent_change_24h": -4.0936, "percent_change_7d": 16.3121, "rank_volume": 643, "rank_mcap": 757, "rank_ratio": 0.8494}, {"ts": 1547942400, "volume_24h": 16089.0, "market_cap": 1067411.0, "price": 0.0152, "percent_change_24h": -7.3171, "percent_change_7d": 5.5556, "rank_volume": 802, "rank_mcap": 773, "rank_ratio": 1.0375}, {"ts": 1548028800, "volume_24h": 35255.0, "market_cap": 1040667.0, "price": 0.0149, "percent_change_24h": -1.9737, "percent_change_7d": -0.6667, "rank_volume": 686, "rank_mcap": 774, "rank_ratio": 0.8863}, {"ts": 1548115200, "volume_24h": 167393.0, "market_cap": 1103845.0, "price": 0.0158, "percent_change_24h": 6.0403, "percent_change_7d": 6.7568, "rank_volume": 426, "rank_mcap": 758, "rank_ratio": 0.562}, {"ts": 1548201600, "volume_24h": 11684.0, "market_cap": 1050649.0, "price": 0.015, "percent_change_24h": -5.0633, "percent_change_7d": 0.0, "rank_volume": 883, "rank_mcap": 766, "rank_ratio": 1.1527}, {"ts": 1548288000, "volume_24h": 31658.0, "market_cap": 1109655.0, "price": 0.0159, "percent_change_24h": 6.0, "percent_change_7d": -5.9172, "rank_volume": 693, "rank_mcap": 751, "rank_ratio": 0.9228}, {"ts": 1548374400, "volume_24h": 6936.0, "market_cap": 1120830.0, "price": 0.016, "percent_change_24h": 0.6289, "percent_change_7d": -6.4327, "rank_volume": 962, "rank_mcap": 746, "rank_ratio": 1.2895}, {"ts": 1548460800, "volume_24h": 13841.0, "market_cap": 1116166.0, "price": 0.0159, "percent_change_24h": -0.625, "percent_change_7d": -3.0488, "rank_volume": 832, "rank_mcap": 753, "rank_ratio": 1.1049}, {"ts": 1548547200, "volume_24h": 2778.0, "market_cap": 1077518.0, "price": 0.0154, "percent_change_24h": -3.1447, "percent_change_7d": 1.3158, "rank_volume": 1091, "rank_mcap": 762, "rank_ratio": 1.4318}, {"ts": 1548633600, "volume_24h": 5295.0, "market_cap": 1035586.0, "price": 0.0148, "percent_change_24h": -3.8961, "percent_change_7d": -0.6711, "rank_volume": 1018, "rank_mcap": 758, "rank_ratio": 1.343}, {"ts": 1548720000, "volume_24h": 4381.0, "market_cap": 1007574.0, "price": 0.0144, "percent_change_24h": -2.7027, "percent_change_7d": -8.8608, "rank_volume": 1030, "rank_mcap": 758, "rank_ratio": 1.3588}, {"ts": 1548806400, "volume_24h": 3533.0, "market_cap": 1058153.0, "price": 0.0151, "percent_change_24h": 4.8611, "percent_change_7d": 0.6667, "rank_volume": 1068, "rank_mcap": 751, "rank_ratio": 1.4221}]